MANIFEST.in
README.md
setup.py
pycache/__init__.py
pycache/cacheDecorator.py
pycache/cacheException.py
pycache/cacheItem.py
pycache/cacheItemInterface.py
pycache/settings.py
pycache/Adapter/CacheItemPoolInterface.py
pycache/Adapter/__init__.py
pycache/Adapter/MongoDB/MongoDBItemPool.py
pycache/Adapter/MongoDB/__init__.py
pycache/Adapter/Redis/RedisItemPool.py
pycache/Adapter/Redis/__init__.py
python_cache.egg-info/PKG-INFO
python_cache.egg-info/SOURCES.txt
python_cache.egg-info/dependency_links.txt
python_cache.egg-info/top_level.txt