Metadata-Version: 1.1
Name: python-cache
Version: 0.0.8
Summary: Pythonic way of Caching
Home-page: https://github.com/python-cache/python-cache
Author: python-cache
Author-email: kevin830222@gmail.com, alan4chen@kimo.com
License: MIT License
Platform: UNKNOWN
Classifier: Programming Language :: Python
Classifier: Programming Language :: Python :: 2
Classifier: Intended Audience :: Developers
